rigel_local_simulation_plugin/__init__.py
rigel_local_simulation_plugin/plugin.py
rigel_local_simulation_plugin-0.1.2.dist-info/LICENSE.md
rigel_local_simulation_plugin-0.1.2.dist-info/WHEEL
rigel_local_simulation_plugin-0.1.2.dist-info/METADATA
rigel_local_simulation_plugin-0.1.2.dist-info/RECORD
