Metadata-Version: 2.1
Name: rigel-local-simulation-plugin
Version: 0.1.2
Summary: A plugin for Rigel to locally run a containerized ROS application.
Author: Pedro Miguel Melo
Author-email: pedro.m.melo@inesctec.pt
Requires-Python: >=3.8,<4.0
Classifier: Programming Language :: Python :: 3
Classifier: Programming Language :: Python :: 3.10
Classifier: Programming Language :: Python :: 3.8
Classifier: Programming Language :: Python :: 3.9
Requires-Dist: docker (>=5.0.3,<6.0.0)
Requires-Dist: rigelcore (>=0.1.16,<0.2.0)
Requires-Dist: roslibpy (>=1.3.0,<2.0.0)
